[
  {
    "id": "event_1",
    "word": "Битва Давида з Голіафом",
    "category": "Події",
    "difficulty": "середній",
    "description": "Давид переміг филистимського велетня Голіафа пращею.",
    "enabled": true
  },
  {
    "id": "event_2",
    "word": "Боротьба Якова з ангелом",
    "category": "Події",
    "difficulty": "експерт",
    "description": "Яків боровся з Ангелом до світанку й отримав ім'я Ізраїль.",
    "enabled": true
  },
  {
    "id": "event_3",
    "word": "В'їзд в Єрусалим",
    "category": "Події",
    "difficulty": "середній",
    "description": "Ісус урочисто в'їхав до Єрусалиму на осляті під радісні вигуки.",
    "enabled": true
  },
  {
    "id": "event_4",
    "word": "Вавилонська вежа",
    "category": "Події",
    "difficulty": "середній",
    "description": "Люди будували вежу до неба, Бог змішав мови.",
    "enabled": true
  },
  {
    "id": "event_5",
    "word": "Вавилонський полон",
    "category": "Події",
    "difficulty": "середній",
    "description": "Жителів Юдеї вивели в полон до Вавилону.",
    "enabled": true
  },
  {
    "id": "event_6",
    "word": "Вихід з Єгипту",
    "category": "Події",
    "difficulty": "середній",
    "description": "Ізраїльтяни покинули Єгипет після десяти кар та Пасхи.",
    "enabled": true
  },
  {
    "id": "event_7",
    "word": "Вознесіння",
    "category": "Події",
    "difficulty": "середній",
    "description": "Ісус вознісся на небо на очах учнів.",
    "enabled": true
  },
  {
    "id": "event_8",
    "word": "Воскресіння",
    "category": "Події",
    "difficulty": "середній",
    "description": "Ісус воскрес із мертвих третього дня після розп'яття.",
    "enabled": true
  },
  {
    "id": "event_9",
    "word": "Воскресіння Лазаря",
    "category": "Події",
    "difficulty": "середній",
    "description": "Ісус воскресив Лазаря з Віфанії після чотирьох днів у гробі.",
    "enabled": true
  },
  {
    "id": "event_10",
    "word": "Втеча до Єгипту",
    "category": "Події",
    "difficulty": "середній",
    "description": "Йосип з Марією та Ісусом втікли до Єгипту від Ірода.",
    "enabled": true
  },
  {
    "id": "event_11",
    "word": "Гріхопадіння",
    "category": "Події",
    "difficulty": "середній",
    "description": "Адам і Єва спожили плід із дерева пізнання добра і зла.",
    "enabled": true
  },
  {
    "id": "event_12",
    "word": "Жертвопринесення Ісака",
    "category": "Події",
    "difficulty": "середній",
    "description": "Бог випробував Авраама, наказавши принести Ісака в жертву.",
    "enabled": true
  },
  {
    "id": "event_13",
    "word": "Зцілення прокаженого",
    "category": "Події",
    "difficulty": "середній",
    "description": "Ісус очистив чоловіка, хворого на проказу.",
    "enabled": true
  },
  {
    "id": "event_14",
    "word": "Зцілення сліпого",
    "category": "Події",
    "difficulty": "середній",
    "description": "Ісус зцілив сліпого від народження чоловіка.",
    "enabled": true
  },
  {
    "id": "event_15",
    "word": "Навернення Савла",
    "category": "Події",
    "difficulty": "експерт",
    "description": "Савл (Павло) зустрів Ісуса на дорозі до Дамаску та навернувся.",
    "enabled": true
  },
  {
    "id": "event_16",
    "word": "Нагірна проповідь",
    "category": "Події",
    "difficulty": "середній",
    "description": "Ісус проголосив Заповіді блаженства та інші науки на горі.",
    "enabled": true
  },
  {
    "id": "event_17",
    "word": "Насичення 5000",
    "category": "Події",
    "difficulty": "середній",
    "description": "Ісус нагодував п'ять хлібинами та двома рибами п'ять тисяч людей.",
    "enabled": true
  },
  {
    "id": "event_18",
    "word": "Обрізання Авраама",
    "category": "Події",
    "difficulty": "експерт",
    "description": "Бог встановив обрізання як знак заповіту з Авраамом.",
    "enabled": true
  },
  {
    "id": "event_19",
    "word": "Обіцянка Аврааму",
    "category": "Події",
    "difficulty": "середній",
    "description": "Бог покликав Авраама та обіцяв йому великий народ і землю.",
    "enabled": true
  },
  {
    "id": "event_20",
    "word": "Отримання Закону на Синаї",
    "category": "Події",
    "difficulty": "середній",
    "description": "Бог дав Мойсеєві Десять Заповідей на горі Синай.",
    "enabled": true
  },
  {
    "id": "event_21",
    "word": "П'ятдесятниця",
    "category": "Події",
    "difficulty": "середній",
    "description": "Святий Дух зійшов на апостолів у вогненних язиках.",
    "enabled": true
  },
  {
    "id": "event_22",
    "word": "Падіння Єрихону",
    "category": "Події",
    "difficulty": "середній",
    "description": "Мури Єрихону впали після обходу ковчегом та сурмлення.",
    "enabled": true
  },
  {
    "id": "event_23",
    "word": "Перехід через Червоне море",
    "category": "Події",
    "difficulty": "середній",
    "description": "Мойсей розділив море, ізраїльтяни перейшли суходолом.",
    "enabled": true
  },
  {
    "id": "event_24",
    "word": "Побиття немовлят",
    "category": "Події",
    "difficulty": "середній",
    "description": "Цар Ірод наказав убити всіх немовлят у Вифлеємі.",
    "enabled": true
  },
  {
    "id": "event_25",
    "word": "Побудова храму",
    "category": "Події",
    "difficulty": "середній",
    "description": "Цар Соломон збудував перший храм Господній в Єрусалимі.",
    "enabled": true
  },
  {
    "id": "event_26",
    "word": "Помазання Давида",
    "category": "Події",
    "difficulty": "середній",
    "description": "Пророк Самуїл помазав Давида на царя над Ізраїлем.",
    "enabled": true
  },
  {
    "id": "event_27",
    "word": "Потоп",
    "category": "Події",
    "difficulty": "середній",
    "description": "Бог наслав потоп на землю, врятувавши Ноя з родиною в ковчезі.",
    "enabled": true
  },
  {
    "id": "event_28",
    "word": "Преображення",
    "category": "Події",
    "difficulty": "середній",
    "description": "Ісус преобразився перед учнями на горі, засяявши як сонце.",
    "enabled": true
  },
  {
    "id": "event_29",
    "word": "Розп'яття",
    "category": "Події",
    "difficulty": "середній",
    "description": "Ісуса Христа розіп'яли на Голгофі.",
    "enabled": true
  },
  {
    "id": "event_30",
    "word": "Різдво Івана Хрестителя",
    "category": "Події",
    "difficulty": "середній",
    "description": "Народження Івана Хрестителя в похилих батьків Захарії та Єлисавети.",
    "enabled": true
  },
  {
    "id": "event_31",
    "word": "Різдво Христове",
    "category": "Події",
    "difficulty": "середній",
    "description": "Ісус Христос народився у Вифлеємі від Діви Марії.",
    "enabled": true
  },
  {
    "id": "event_32",
    "word": "Спокуса в пустелі",
    "category": "Події",
    "difficulty": "середній",
    "description": "Ісус постив сорок днів у пустелі та відкинув спокуси диявола.",
    "enabled": true
  },
  {
    "id": "event_33",
    "word": "Створення світу",
    "category": "Події",
    "difficulty": "середній",
    "description": "Бог створив небо та землю за шість днів.",
    "enabled": true
  },
  {
    "id": "event_34",
    "word": "Стрітення",
    "category": "Події",
    "difficulty": "експерт",
    "description": "Принесення Ісуса до храму на сороковий день після народження.",
    "enabled": true
  },
  {
    "id": "event_35",
    "word": "Суд Соломона",
    "category": "Події",
    "difficulty": "середній",
    "description": "Соломон мудро розсудив суперечку двох жінок про дитину.",
    "enabled": true
  },
  {
    "id": "event_36",
    "word": "Таємна вечеря",
    "category": "Події",
    "difficulty": "середній",
    "description": "Ісус з учнями спожив останню пасхальну вечерю перед розп'яттям.",
    "enabled": true
  },
  {
    "id": "event_37",
    "word": "Успіння Богородиці",
    "category": "Події",
    "difficulty": "експерт",
    "description": "Матір Ісуса Марія перебувала з апостолами після Вознесіння.",
    "enabled": true
  },
  {
    "id": "event_38",
    "word": "Усікновення голови Івана",
    "category": "Події",
    "difficulty": "експерт",
    "description": "Ірод наказав відтяти голову Іванові Хрестителю.",
    "enabled": true
  },
  {
    "id": "event_39",
    "word": "Ходіння по воді",
    "category": "Події",
    "difficulty": "середній",
    "description": "Ісус пішов по воді до учнів, яких застав шторм на озері.",
    "enabled": true
  },
  {
    "id": "event_40",
    "word": "Хрещення Господнє",
    "category": "Події",
    "difficulty": "середній",
    "description": "Іван Хреститель хрестив Ісуса в річці Йордан.",
    "enabled": true
  }
]